file_reader/__init__.py
file_reader-0.2.3.dist-info/METADATA
file_reader-0.2.3.dist-info/WHEEL
file_reader-0.2.3.dist-info/RECORD
